sagemaker_inference_gpu/__init__.py
sagemaker_inference_gpu/content_types.py
sagemaker_inference_gpu/decoder.py
sagemaker_inference_gpu/default_handler_service.py
sagemaker_inference_gpu/default_inference_handler.py
sagemaker_inference_gpu/encoder.py
sagemaker_inference_gpu/environment.py
sagemaker_inference_gpu/errors.py
sagemaker_inference_gpu/logging.py
sagemaker_inference_gpu/model_server.py
sagemaker_inference_gpu/parameters.py
sagemaker_inference_gpu/transformer.py
sagemaker_inference_gpu/utils.py
sagemaker_inference_gpu/etc/default-mms.properties
sagemaker_inference_gpu/etc/log4j2.xml
sagemaker_inference_gpu/etc/mme-mms.properties
sagemaker_inference_gpu-0.10.2.dist-info/LICENSE
sagemaker_inference_gpu-0.10.2.dist-info/METADATA
sagemaker_inference_gpu-0.10.2.dist-info/NOTICE
sagemaker_inference_gpu-0.10.2.dist-info/WHEEL
sagemaker_inference_gpu-0.10.2.dist-info/top_level.txt
sagemaker_inference_gpu-0.10.2.dist-info/RECORD
