Metadata-Version: 2.1
Name: sagemaker_inference_gpu
Version: 0.10.2
Summary: (Altered to work with multi-model-server-gpu) Open source toolkit for helping create serving containers to run on Amazon SageMaker.
Home-page: https://github.com/aws/sagemaker-inference-toolkit/
Author: Amazon Web Services
License: Apache License 2.0
Classifier: Intended Audience :: Developers
Classifier: Natural Language :: English
Classifier: License :: OSI Approved :: Apache Software License
Classifier: Programming Language :: Python
Classifier: Programming Language :: Python :: 3.8
Classifier: Programming Language :: Python :: 3.9
Classifier: Programming Language :: Python :: 3.10
License-File: LICENSE
License-File: NOTICE
Requires-Dist: boto3
Requires-Dist: numpy
Requires-Dist: six
Requires-Dist: psutil
Requires-Dist: retrying <1.4,>=1.3.3
Requires-Dist: scipy
Provides-Extra: test
Requires-Dist: tox ; extra == 'test'
Requires-Dist: flake8 ; extra == 'test'
Requires-Dist: pytest ; extra == 'test'
Requires-Dist: pytest-xdist ; extra == 'test'
Requires-Dist: pytest-cov ; extra == 'test'
Requires-Dist: mock ; extra == 'test'
Requires-Dist: requests ; extra == 'test'
